Metadata-Version: 2.4
Name: awex
Version: 0.2.0
Summary: High-performance RL training-inference weight synchronization framework
Author-email: chaokunyang <shawn.ck.yang@gmail.com>
Maintainer-email: chaokunyang <shawn.ck.yang@gmail.com>
License: Apache-2.0
Project-URL: Homepage, https://github.com/inclusionAI/awex
Project-URL: Repository, https://github.com/inclusionAI/awex
Project-URL: Issues, https://github.com/inclusionAI/awex/issues
Project-URL: Documentation, https://github.com/inclusionAI/awex
Keywords: machine learning,deep learning,reinforcement learning,distributed training,weight synchronization
Classifier: Development Status :: 3 - Alpha
Classifier: Intended Audience :: Developers
Classifier: Intended Audience :: Science/Research
Classifier: License :: OSI Approved :: Apache Software License
Classifier: Operating System :: POSIX :: Linux
Classifier: Programming Language :: Python :: 3
Classifier: Programming Language :: Python :: 3.8
Classifier: Programming Language :: Python :: 3.9
Classifier: Programming Language :: Python :: 3.10
Classifier: Programming Language :: Python :: 3.11
Classifier: Programming Language :: Python :: 3.12
Classifier: Topic :: Scientific/Engineering :: Artificial Intelligence
Classifier: Topic :: System :: Distributed Computing
Requires-Python: >=3.8
License-File: LICENSE
Provides-Extra: dev
Requires-Dist: modelscope>=1.9.0; extra == "dev"
Dynamic: license-file
